{"cameraMode":{"drawMode":0,"name":"Shaded","section":"Shading Mode"},"sceneLighting":true,"audioPlay":false,"sceneViewState":{"m_AlwaysRefresh":false,"showFog":true,"showSkybox":true,"showFlares":true,"showImageEffects":true,"showParticleSystems":true,"showVisualEffectGraphs":true,"m_FxEnabled":true},"in2DMode":false,"pivot":{"x":4.874075412750244,"y":2.281135082244873,"z":3.796529769897461},"rotation":{"x":0.23999235033988954,"y":0.06982432305812836,"z":-0.017309263348579408,"w":0.9681062698364258},"size":18.348464965820314,"orthographic":false}